t2qc/__init__.py
t2qc/__version__.py
t2qc/bids/__init__.py
t2qc/cli/__init__.py
t2qc/cli/get.py
t2qc/cli/process.py
t2qc/cli/tandem.py
t2qc/commons/__init__.py
t2qc/config/__init__.py
t2qc/config/t2qc.yaml
t2qc/snapshots/__init__.py
t2qc/state/__init__.py
t2qc/tasks/__init__.py
t2qc/tasks/mriqc.py
t2qc/tasks/vnav.py
t2qc/xnat/__init__.py
t2qc-0.3.3.data/scripts/t2QC.py
t2qc-0.3.3.dist-info/LICENSE
t2qc-0.3.3.dist-info/METADATA
t2qc-0.3.3.dist-info/WHEEL
t2qc-0.3.3.dist-info/top_level.txt
t2qc-0.3.3.dist-info/RECORD
