Metadata-Version: 2.1
Name: t2qc
Version: 0.3.3
Summary: T2 QC
Home-page: https://github.com/harvard-nrg/t2qc
Author: Neuroinformatics Research Group
Author-email: info@neuroinfo.org
License: UNKNOWN
Platform: UNKNOWN
Requires-Dist: yaxil
Requires-Dist: retry
Requires-Dist: natsort
Requires-Dist: pillow
Requires-Dist: nibabel
Requires-Dist: selfie
Requires-Dist: executors
Requires-Dist: vnav
